AUTHORS.rst
CONTRIBUTING.rst
HISTORY.rst
LICENSE
MANIFEST.in
README.rst
requirements-test.txt
requirements.txt
setup.cfg
setup.py
bank/__init__.py
bank/exceptions.py
bank/locks.py
bank/models.py
bank/models/__init__.py
bank/models/account.py
bank/models/lock.py
bank/models/transaction.py
django_bank.egg-info/PKG-INFO
django_bank.egg-info/SOURCES.txt
django_bank.egg-info/dependency_links.txt
django_bank.egg-info/not-zip-safe
django_bank.egg-info/top_level.txt