Metadata-Version: 1.1
Name: django-bank
Version: 0.1.0
Summary: Small Django app helping you to handle your users accounts
Home-page: https://github.com/niktto/django-bank
Author: Marek Szwalkiewicz
Author-email: marek@szwalkiewicz.waw.pl
License: BSD
Keywords: django-bank
Platform: UNKNOWN
Classifier: Development Status :: 2 - Pre-Alpha
Classifier: Framework :: Django
Classifier: Intended Audience :: Developers
Classifier: License :: OSI Approved :: MIT License
Classifier: Natural Language :: English
Classifier: Programming Language :: Python :: 2
Classifier: Programming Language :: Python :: 2.7
Classifier: Programming Language :: Python :: 3
Classifier: Programming Language :: Python :: 3.4
